procedural_buildings/BoxSplitter.py
procedural_buildings/ContextObj.py
procedural_buildings/ObjReader.py
procedural_buildings/Ops.py
procedural_buildings/Primitive.py
procedural_buildings/Processor.py
procedural_buildings/RandRange.py
procedural_buildings/RandomOpGraph.py
procedural_buildings/Scope.py
procedural_buildings/__init__.py
procedural_buildings/__main__.py
procedural_buildings/grammarToBuildings.py
procedural_buildings/parsing/Checker.py
procedural_buildings/parsing/GrammarParser.py
procedural_buildings/parsing/Lexer.py
procedural_buildings/parsing/Parser.py
procedural_buildings/parsing/ParserAbstract.py
procedural_buildings/parsing/Rule.py
procedural_buildings/parsing/__init__.py
procedural_buildings/primitives/cabinEntrance.obj
procedural_buildings/primitives/cabinRoof.obj
procedural_buildings/primitives/cabinWindow.obj
procedural_buildings/primitives/corner.obj
procedural_buildings/primitives/door.obj
procedural_buildings/primitives/garage.obj
procedural_buildings/primitives/hip.obj
procedural_buildings/primitives/pyramid.obj
procedural_buildings/primitives/rect.obj
procedural_buildings/primitives/rect_old.obj
procedural_buildings/primitives/right_angle_triangle.obj
procedural_buildings/primitives/roofCorner.obj
procedural_buildings/primitives/triangle.obj
procedural_buildings/primitives/trough.obj
procedural_buildings/primitives/window2.obj
procedural_buildings/primitives/window3.obj
procedural_buildings-1.0.1.dist-info/LICENSE
procedural_buildings-1.0.1.dist-info/METADATA
procedural_buildings-1.0.1.dist-info/WHEEL
procedural_buildings-1.0.1.dist-info/top_level.txt
procedural_buildings-1.0.1.dist-info/RECORD
