Metadata-Version: 2.1
Name: procedural-buildings
Version: 1.0.1
Summary: Tools for the procedural modelling of buildings
Home-page: https://github.com/JUST0M/procedural-buildings
Author: Tom Mason
Author-email: tommasonuk@yahoo.co.uk
License: UNKNOWN
Platform: UNKNOWN
Classifier: Programming Language :: Python :: 3
Classifier: License :: OSI Approved :: MIT License
Classifier: Operating System :: OS Independent
Requires-Python: >=3.6
Requires-Dist: numpy
Requires-Dist: sympy
Requires-Dist: sly
